torchperf/__init__.py
torchperf/info.py
torchperf/measure.py
torchperf/recipe.py
pytorch_perf-0.0.3.dist-info/LICENSE
pytorch_perf-0.0.3.dist-info/METADATA
pytorch_perf-0.0.3.dist-info/WHEEL
pytorch_perf-0.0.3.dist-info/top_level.txt
pytorch_perf-0.0.3.dist-info/RECORD
