Metadata-Version: 2.1
Name: pytorch-perf
Version: 0.0.3
Summary: A pytorch perf decorator
Home-page: https://github.com/yhren/torchperf
Author: Yihui Ren
Author-email: yren@bnl.gov
License: BSD-3
Keywords: decorator cuda performance perf pytorch
Classifier: License :: OSI Approved :: BSD License
Classifier: Development Status :: 2 - Pre-Alpha
Classifier: Programming Language :: Python :: 3.7
Classifier: Programming Language :: Python :: 3.8
Classifier: Programming Language :: Python :: 3.9
Classifier: Programming Language :: Python :: 3.10
Classifier: Programming Language :: Python :: 3.11
Classifier: Operating System :: POSIX :: Linux
Requires-Python: >=3.7
License-File: LICENSE
Requires-Dist: numpy
